miRe2e/__init__.py
miRe2e/aux.py
miRe2e/data_process.py
miRe2e/encoder.py
miRe2e/focal_loss.py
miRe2e/get_error.py
miRe2e/mfe.py
miRe2e/mire2e.py
miRe2e/positional_encoding.py
miRe2e/predictor.py
miRe2e/preprocessor.py
miRe2e/resnet.py
miRe2e/structure.py
miRe2e-0.17.dist-info/LICENSE
miRe2e-0.17.dist-info/METADATA
miRe2e-0.17.dist-info/WHEEL
miRe2e-0.17.dist-info/top_level.txt
miRe2e-0.17.dist-info/RECORD
