Metadata-Version: 2.1
Name: miRe2e
Version: 0.17
Summary: An end-to-end deep neural network based on Transformers for pre-miRNA prediction
Home-page: https://github.com/sinc-lab/miRe2e
Author: Jonathan Raad
Author-email: jraad@sinc.unl.edu.ar
License: UNKNOWN
Project-URL: Webdemo, https://sinc.unl.edu.ar/web-demo/miRe2e/
Platform: UNKNOWN
Classifier: Programming Language :: Python :: 3
Classifier: License :: OSI Approved :: MIT License
Classifier: Operating System :: OS Independent
Requires-Python: >=3.7
Requires-Dist: torch (>=1.7)
Requires-Dist: biopython (>=1.78)
Requires-Dist: scikit-learn (>=0.23)
Requires-Dist: tqdm
